<?xml version="1.0" encoding="UTF-8"?>
<MetaDataObject xmlns="http://v8.1c.ru/8.3/MDClasses" xmlns:app="http://v8.1c.ru/8.2/managed-application/core" xmlns:cfg="http://v8.1c.ru/8.1/data/enterprise/current-config" xmlns:cmi="http://v8.1c.ru/8.2/managed-application/cmi" xmlns:ent="http://v8.1c.ru/8.1/data/enterprise" xmlns:lf="http://v8.1c.ru/8.2/managed-application/logform" xmlns:style="http://v8.1c.ru/8.1/data/ui/style" xmlns:sys="http://v8.1c.ru/8.1/data/ui/fonts/system" xmlns:v8="http://v8.1c.ru/8.1/data/core" xmlns:v8ui="http://v8.1c.ru/8.1/data/ui" xmlns:web="http://v8.1c.ru/8.1/data/ui/colors/web" xmlns:win="http://v8.1c.ru/8.1/data/ui/colors/windows" xmlns:xen="http://v8.1c.ru/8.3/xcf/enums" xmlns:xpr="http://v8.1c.ru/8.3/xcf/predef" xmlns:xr="http://v8.1c.ru/8.3/xcf/readable" xmlns:xs="http://www.w3.org/2001/XMLSchema" xmlns:xsi="http://www.w3.org/2001/XMLSchema-instance" version="2.5">
	<WebService uuid="3cc43e96-684a-4983-888a-6761c19850b5">
		<Properties>
			<Name>Temple</Name>
			<Synonym>
				<v8:item>
					<v8:lang>ru</v8:lang>
					<v8:content>Temple</v8:content>
				</v8:item>
			</Synonym>
			<Comment/>
			<Namespace>www.uri.com</Namespace>
			<XDTOPackages/>
			<DescriptorFileName>Temple.1cws</DescriptorFileName>
			<ReuseSessions>AutoUse</ReuseSessions>
			<SessionMaxAge>20</SessionMaxAge>
		</Properties>
		<ChildObjects>
			<Operation uuid="a6701c8b-765b-41c2-9f2b-7b6c7d96eb75">
				<Properties>
					<Name>DocsSynchron</Name>
					<Synonym>
						<v8:item>
							<v8:lang>ru</v8:lang>
							<v8:content>Docs synchron</v8:content>
						</v8:item>
					</Synonym>
					<Comment/>
					<XDTOReturningValueType>xs:string</XDTOReturningValueType>
					<Nillable>false</Nillable>
					<Transactioned>false</Transactioned>
					<ProcedureName>DocsSynchron</ProcedureName>
					<DataLockControlMode>Managed</DataLockControlMode>
				</Properties>
				<ChildObjects>
					<Parameter uuid="8a74bc6c-d5e8-4189-a486-e03a5f44393d">
						<Properties>
							<Name>Param</Name>
							<Synonym>
								<v8:item>
									<v8:lang>ru</v8:lang>
									<v8:content>Param</v8:content>
								</v8:item>
							</Synonym>
							<Comment/>
							<XDTOValueType>xs:string</XDTOValueType>
							<Nillable>false</Nillable>
							<TransferDirection>In</TransferDirection>
						</Properties>
					</Parameter>
				</ChildObjects>
			</Operation>
		</ChildObjects>
	</WebService>
</MetaDataObject>